{
    "Id": "authored_closure_498743331",
    "StageId": 3,
    "StageName": "Hard",
    "AuthoredCardCount": 77,
    "ClosureCardCount": 5,
    "Seed": 498743331,
    "Placements": [
        {
            "ShapeId": "CURVE_DIAG_TRANS_1x1",
            "X": 49,
            "Y": 50,
            "Facing": 6
        },
        {
            "ShapeId": "STRAIGHT_DIAG_1x1",
            "X": 46,
            "Y": 51,
            "Facing": 2
        },
        {
            "ShapeId": "LCURVE_DIAG_TRANS_1x1",
            "X": 45,
            "Y": 52,
            "Facing": 4
        },
        {
            "ShapeId": "STRAIGHT_1x1",
            "X": 45,
            "Y": 53,
            "Facing": 4
        },
        {
            "ShapeId": "LCURVE_1x1",
            "X": 45,
            "Y": 54,
            "Facing": 6
        },
        {
            "ShapeId": "CURVE_DIAG_TRANS_1x1",
            "X": 46,
            "Y": 54,
            "Facing": 2
        },
        {
            "ShapeId": "LCURVE_DIAG_TRANS_1x1",
            "X": 47,
            "Y": 53,
            "Facing": 0
        },
        {
            "ShapeId": "LCURVE_DIAG_TRANS_1x1",
            "X": 47,
            "Y": 52,
            "Facing": 4
        },
        {
            "ShapeId": "STRAIGHT_DIAG_1x1",
            "X": 48,
            "Y": 51,
            "Facing": 6
        },
        {
            "ShapeId": "STRAIGHT_DIAG_1x1",
            "X": 47,
            "Y": 50,
            "Facing": 6
        },
        {
            "ShapeId": "STRAIGHT_DIAG_1x1",
            "X": 48,
            "Y": 49,
            "Facing": 6
        },
        {
            "ShapeId": "STRAIGHT_DIAG_1x1",
            "X": 58,
            "Y": 42,
            "Facing": 0
        },
        {
            "ShapeId": "LCURVE_DIAG_TRANS_1x1",
            "X": 57,
            "Y": 41,
            "Facing": 2
        },
        {
            "ShapeId": "STRAIGHT_1x1",
            "X": 56,
            "Y": 41,
            "Facing": 2
        },
        {
            "ShapeId": "CURVE_DIAG_TRANS_1x1",
            "X": 55,
            "Y": 41,
            "Facing": 6
        },
        {
            "ShapeId": "STRAIGHT_DIAG_1x1",
            "X": 54,
            "Y": 42,
            "Facing": 2
        },
        {
            "ShapeId": "STRAIGHT_DIAG_1x1",
            "X": 53,
            "Y": 43,
            "Facing": 2
        },
        {
            "ShapeId": "STRAIGHT_DIAG_1x1",
            "X": 52,
            "Y": 44,
            "Facing": 2
        },
        {
            "ShapeId": "LCURVE_DIAG_TRANS_1x1",
            "X": 51,
            "Y": 45,
            "Facing": 4
        },
        {
            "ShapeId": "LCURVE_DIAG_TRANS_1x1",
            "X": 51,
            "Y": 46,
            "Facing": 0
        },
        {
            "ShapeId": "STRAIGHT_DIAG_1x1",
            "X": 50,
            "Y": 47,
            "Facing": 2
        },
        {
            "ShapeId": "STRAIGHT_DIAG_1x1",
            "X": 49,
            "Y": 48,
            "Facing": 2
        },
        {
            "ShapeId": "STRAIGHT_DIAG_1x1",
            "X": 59,
            "Y": 43,
            "Facing": 4
        },
        {
            "ShapeId": "STRAIGHT_DIAG_1x1",
            "X": 60,
            "Y": 44,
            "Facing": 4
        },
        {
            "ShapeId": "CURVE_DIAG_TRANS_1x1",
            "X": 61,
            "Y": 45,
            "Facing": 4
        },
        {
            "ShapeId": "STRAIGHT_1x1",
            "X": 60,
            "Y": 48,
            "Facing": 0
        },
        {
            "ShapeId": "CURVE_1x1",
            "X": 60,
            "Y": 47,
            "Facing": 6
        },
        {
            "ShapeId": "LCURVE_1x1",
            "X": 61,
            "Y": 47,
            "Facing": 0
        },
        {
            "ShapeId": "STRAIGHT_1x1",
            "X": 61,
            "Y": 46,
            "Facing": 0
        },
        {
            "ShapeId": "STRAIGHT_1x1",
            "X": 60,
            "Y": 50,
            "Facing": 0
        },
        {
            "ShapeId": "STRAIGHT_1x1",
            "X": 60,
            "Y": 49,
            "Facing": 0
        },
        {
            "ShapeId": "CURVE_1x1",
            "X": 60,
            "Y": 51,
            "Facing": 0
        },
        {
            "ShapeId": "CURVE_1x1",
            "X": 61,
            "Y": 51,
            "Facing": 2
        },
        {
            "ShapeId": "STRAIGHT_1x1",
            "X": 61,
            "Y": 50,
            "Facing": 0
        },
        {
            "ShapeId": "STRAIGHT_1x1",
            "X": 62,
            "Y": 46,
            "Facing": 4
        },
        {
            "ShapeId": "LCURVE_DIAG_TRANS_1x1",
            "X": 62,
            "Y": 47,
            "Facing": 0
        },
        {
            "ShapeId": "LCURVE_DIAG_TRANS_1x1",
            "X": 61,
            "Y": 48,
            "Facing": 4
        },
        {
            "ShapeId": "STRAIGHT_1x1",
            "X": 61,
            "Y": 49,
            "Facing": 4
        },
        {
            "ShapeId": "STRAIGHT_1x1",
            "X": 63,
            "Y": 43,
            "Facing": 4
        },
        {
            "ShapeId": "CURVE_1x1",
            "X": 63,
            "Y": 44,
            "Facing": 2
        },
        {
            "ShapeId": "LCURVE_1x1",
            "X": 62,
            "Y": 44,
            "Facing": 4
        },
        {
            "ShapeId": "STRAIGHT_1x1",
            "X": 62,
            "Y": 45,
            "Facing": 4
        },
        {
            "ShapeId": "CURVE_1x1",
            "X": 63,
            "Y": 42,
            "Facing": 4
        },
        {
            "ShapeId": "CURVE_1x1",
            "X": 62,
            "Y": 42,
            "Facing": 0
        },
        {
            "ShapeId": "STRAIGHT_1x1",
            "X": 62,
            "Y": 31,
            "Facing": 4
        },
        {
            "ShapeId": "STRAIGHT_1x1",
            "X": 62,
            "Y": 32,
            "Facing": 4
        },
        {
            "ShapeId": "STRAIGHT_1x1",
            "X": 62,
            "Y": 33,
            "Facing": 4
        },
        {
            "ShapeId": "STRAIGHT_1x1",
            "X": 62,
            "Y": 40,
            "Facing": 4
        },
        {
            "ShapeId": "STRAIGHT_1x1",
            "X": 62,
            "Y": 41,
            "Facing": 4
        },
        {
            "ShapeId": "STRAIGHT_1x1",
            "X": 62,
            "Y": 39,
            "Facing": 4
        },
        {
            "ShapeId": "STRAIGHT_1x1",
            "X": 62,
            "Y": 38,
            "Facing": 4
        },
        {
            "ShapeId": "STRAIGHT_1x1",
            "X": 62,
            "Y": 37,
            "Facing": 4
        },
        {
            "ShapeId": "STRAIGHT_1x1",
            "X": 62,
            "Y": 36,
            "Facing": 4
        },
        {
            "ShapeId": "STRAIGHT_1x1",
            "X": 62,
            "Y": 35,
            "Facing": 4
        },
        {
            "ShapeId": "STRAIGHT_1x1",
            "X": 62,
            "Y": 34,
            "Facing": 4
        },
        {
            "ShapeId": "STRAIGHT_1x1",
            "X": 64,
            "Y": 29,
            "Facing": 0
        },
        {
            "ShapeId": "LCURVE_1x1",
            "X": 64,
            "Y": 28,
            "Facing": 2
        },
        {
            "ShapeId": "CURVE_DIAG_TRANS_1x1",
            "X": 63,
            "Y": 28,
            "Facing": 6
        },
        {
            "ShapeId": "LCURVE_DIAG_TRANS_1x1",
            "X": 62,
            "Y": 29,
            "Facing": 4
        },
        {
            "ShapeId": "STRAIGHT_1x1",
            "X": 62,
            "Y": 30,
            "Facing": 4
        },
        {
            "ShapeId": "STRAIGHT_1x1",
            "X": 64,
            "Y": 40,
            "Facing": 0
        },
        {
            "ShapeId": "STRAIGHT_1x1",
            "X": 64,
            "Y": 39,
            "Facing": 0
        },
        {
            "ShapeId": "STRAIGHT_1x1",
            "X": 64,
            "Y": 38,
            "Facing": 0
        },
        {
            "ShapeId": "STRAIGHT_1x1",
            "X": 64,
            "Y": 31,
            "Facing": 0
        },
        {
            "ShapeId": "STRAIGHT_1x1",
            "X": 64,
            "Y": 30,
            "Facing": 0
        },
        {
            "ShapeId": "STRAIGHT_1x1",
            "X": 64,
            "Y": 32,
            "Facing": 0
        },
        {
            "ShapeId": "STRAIGHT_1x1",
            "X": 64,
            "Y": 33,
            "Facing": 0
        },
        {
            "ShapeId": "STRAIGHT_1x1",
            "X": 64,
            "Y": 34,
            "Facing": 0
        },
        {
            "ShapeId": "STRAIGHT_1x1",
            "X": 64,
            "Y": 35,
            "Facing": 0
        },
        {
            "ShapeId": "STRAIGHT_1x1",
            "X": 64,
            "Y": 36,
            "Facing": 0
        },
        {
            "ShapeId": "STRAIGHT_1x1",
            "X": 64,
            "Y": 37,
            "Facing": 0
        },
        {
            "ShapeId": "STRAIGHT_1x1",
            "X": 64,
            "Y": 41,
            "Facing": 4
        },
        {
            "ShapeId": "STRAIGHT_1x1",
            "X": 64,
            "Y": 42,
            "Facing": 4
        },
        {
            "ShapeId": "STRAIGHT_1x1",
            "X": 65,
            "Y": 46,
            "Facing": 0
        },
        {
            "ShapeId": "CURVE_DIAG_TRANS_1x1",
            "X": 65,
            "Y": 45,
            "Facing": 4
        },
        {
            "ShapeId": "CURVE_DIAG_TRANS_1x1",
            "X": 64,
            "Y": 44,
            "Facing": 0
        },
        {
            "ShapeId": "STRAIGHT_1x1",
            "X": 64,
            "Y": 43,
            "Facing": 0
        },
        {
            "ShapeId": "STRAIGHT_1x1",
            "X": 60,
            "Y": 52,
            "Facing": 6
        },
        {
            "ShapeId": "CURVE_DIAG_TRANS_1x1",
            "X": 61,
            "Y": 52,
            "Facing": 2
        },
        {
            "ShapeId": "LCURVE_DIAG_TRANS_1x1",
            "X": 62,
            "Y": 51,
            "Facing": 0
        },
        {
            "ShapeId": "LCURVE_DIAG_TRANS_1x1",
            "X": 62,
            "Y": 50,
            "Facing": 4
        },
        {
            "ShapeId": "CURVE_DIAG_TRANS_1x1",
            "X": 63,
            "Y": 49,
            "Facing": 6
        },
        {
            "ShapeId": "STRAIGHT_1x1",
            "X": 65,
            "Y": 47,
            "Facing": 0
        },
        {
            "ShapeId": "LCURVE_DIAG_TRANS_1x1",
            "X": 65,
            "Y": 48,
            "Facing": 0
        },
        {
            "ShapeId": "CURVE_DIAG_TRANS_1x1",
            "X": 64,
            "Y": 49,
            "Facing": 2
        },
        {
            "ShapeId": "STRAIGHT_1x1",
            "X": 58,
            "Y": 50,
            "Facing": 6
        },
        {
            "ShapeId": "CURVE_1x1",
            "X": 59,
            "Y": 50,
            "Facing": 4
        },
        {
            "ShapeId": "CURVE_1x1",
            "X": 59,
            "Y": 51,
            "Facing": 2
        },
        {
            "ShapeId": "LCURVE_1x1",
            "X": 58,
            "Y": 51,
            "Facing": 4
        },
        {
            "ShapeId": "LCURVE_1x1",
            "X": 58,
            "Y": 52,
            "Facing": 6
        },
        {
            "ShapeId": "STRAIGHT_1x1",
            "X": 59,
            "Y": 52,
            "Facing": 6
        },
        {
            "ShapeId": "STRAIGHT_1x1",
            "X": 57,
            "Y": 50,
            "Facing": 2
        },
        {
            "ShapeId": "STRAIGHT_1x1",
            "X": 56,
            "Y": 50,
            "Facing": 2
        },
        {
            "ShapeId": "STRAIGHT_1x1",
            "X": 55,
            "Y": 50,
            "Facing": 2
        },
        {
            "ShapeId": "STRAIGHT_1x1",
            "X": 54,
            "Y": 50,
            "Facing": 2
        },
        {
            "ShapeId": "STRAIGHT_1x1",
            "X": 53,
            "Y": 50,
            "Facing": 2
        },
        {
            "ShapeId": "STRAIGHT_1x1",
            "X": 52,
            "Y": 50,
            "Facing": 2
        },
        {
            "ShapeId": "STRAIGHT_1x1",
            "X": 51,
            "Y": 50,
            "Facing": 2
        },
        {
            "ShapeId": "STRAIGHT_1x1",
            "X": 50,
            "Y": 50,
            "Facing": 2
        }
    ],
    "ClosureSegments": [
        {
        },
        {
        },
        {
        },
        {
            "Anchors": [
                {
                    "X": 122.0,
                    "Z": 103.0
                },
                {
                    "X": 122.1950912475586,
                    "Z": 102.98078155517578
                },
                {
                    "X": 122.38268280029297,
                    "Z": 102.92388153076172
                },
                {
                    "X": 122.55557250976563,
                    "Z": 102.83146667480469
                },
                {
                    "X": 122.70710754394531,
                    "Z": 102.70710754394531
                },
                {
                    "X": 122.83146667480469,
                    "Z": 102.55557250976563
                },
                {
                    "X": 122.92388153076172,
                    "Z": 102.38268280029297
                },
                {
                    "X": 122.98078155517578,
                    "Z": 102.1950912475586
                },
                {
                    "X": 123.0,
                    "Z": 102.0
                }
            ]
        },
        {
            "Anchors": [
                {
                    "X": 123.0,
                    "Z": 100.0
                },
                {
                    "X": 123.0,
                    "Z": 102.0
                }
            ]
        },
        {
            "Anchors": [
                {
                    "X": 127.0,
                    "Z": 86.0
                },
                {
                    "X": 126.98078918457031,
                    "Z": 85.8049087524414
                },
                {
                    "X": 126.92388153076172,
                    "Z": 85.61731719970703
                },
                {
                    "X": 126.83146667480469,
                    "Z": 85.44442749023438
                },
                {
                    "X": 126.70710754394531,
                    "Z": 85.29289245605469
                },
                {
                    "X": 126.55557250976563,
                    "Z": 85.16853332519531
                },
                {
                    "X": 126.38268280029297,
                    "Z": 85.07611846923828
                },
                {
                    "X": 126.1950912475586,
                    "Z": 85.01921844482422
                },
                {
                    "X": 126.0,
                    "Z": 85.0
                }
            ]
        },
        {
            "Anchors": [
                {
                    "X": 125.0,
                    "Z": 84.0
                },
                {
                    "X": 125.01921081542969,
                    "Z": 84.1950912475586
                },
                {
                    "X": 125.07611846923828,
                    "Z": 84.38268280029297
                },
                {
                    "X": 125.16853332519531,
                    "Z": 84.55557250976563
                },
                {
                    "X": 125.29289245605469,
                    "Z": 84.70710754394531
                },
                {
                    "X": 125.44442749023438,
                    "Z": 84.83146667480469
                },
                {
                    "X": 125.61731719970703,
                    "Z": 84.92388153076172
                },
                {
                    "X": 125.8049087524414,
                    "Z": 84.98078155517578
                },
                {
                    "X": 126.0,
                    "Z": 85.0
                }
            ]
        },
        {
            "Anchors": [
                {
                    "X": 114.0,
                    "Z": 101.0
                },
                {
                    "X": 116.0,
                    "Z": 101.0
                }
            ]
        },
        {
            "Anchors": [
                {
                    "X": 112.0,
                    "Z": 101.0
                },
                {
                    "X": 114.0,
                    "Z": 101.0
                }
            ]
        },
        {
            "Anchors": [
                {
                    "X": 110.0,
                    "Z": 101.0
                },
                {
                    "X": 112.0,
                    "Z": 101.0
                }
            ]
        },
        {
            "Anchors": [
                {
                    "X": 108.0,
                    "Z": 101.0
                },
                {
                    "X": 110.0,
                    "Z": 101.0
                }
            ]
        },
        {
            "Anchors": [
                {
                    "X": 106.0,
                    "Z": 101.0
                },
                {
                    "X": 108.0,
                    "Z": 101.0
                }
            ]
        },
        {
            "Anchors": [
                {
                    "X": 104.0,
                    "Z": 101.0
                },
                {
                    "X": 106.0,
                    "Z": 101.0
                }
            ]
        },
        {
            "Anchors": [
                {
                    "X": 102.0,
                    "Z": 101.0
                },
                {
                    "X": 104.0,
                    "Z": 101.0
                }
            ]
        },
        {
            "Anchors": [
                {
                    "X": 100.0,
                    "Z": 101.0
                },
                {
                    "X": 102.0,
                    "Z": 101.0
                }
            ]
        }
    ],"Anchors":[[150,151.5],[149.613,151.535],[149.209,151.635],[148.798,151.788],[148.39,151.985],[147.996,152.215],[147.626,152.467],[147.291,152.733],[147,153],[144,156],[143.733,156.291],[143.467,156.626],[143.215,156.996],[142.985,157.39],[142.788,157.798],[142.635,158.209],[142.535,158.613],[142.5,159],[142.465,159.387],[142.365,159.791],[142.212,160.202],[142.015,160.61],[141.785,161.004],[141.533,161.374],[141.268,161.709],[141,162],[140.709,162.268],[140.374,162.533],[140.004,162.785],[139.61,163.015],[139.202,163.212],[138.791,163.365],[138.387,163.465],[138,163.5],[137.707,163.471],[137.426,163.386],[137.167,163.247],[136.939,163.061],[136.753,162.833],[136.614,162.574],[136.529,162.293],[136.5,162],[136.5,159],[136.535,158.613],[136.635,158.209],[136.788,157.798],[136.985,157.39],[137.215,156.996],[137.467,156.626],[137.733,156.291],[138,156],[141,153],[144,150],[147,147],[150,144],[153,141],[153.268,140.709],[153.533,140.374],[153.785,140.004],[154.015,139.61],[154.212,139.202],[154.365,138.791],[154.465,138.387],[154.5,138],[154.535,137.613],[154.635,137.209],[154.788,136.798],[154.985,136.39],[155.215,135.996],[155.467,135.626],[155.733,135.291],[156,135],[159,132],[162,129],[165,126],[165.291,125.733],[165.626,125.467],[165.996,125.215],[166.39,124.985],[166.798,124.788],[167.209,124.635],[167.613,124.536],[168,124.5],[171,124.5],[171.387,124.536],[171.791,124.635],[172.202,124.788],[172.61,124.985],[173.004,125.215],[173.374,125.467],[173.709,125.733],[174,126],[177,129],[180,132],[183,135],[183.268,135.291],[183.533,135.626],[183.785,135.996],[184.015,136.39],[184.212,136.798],[184.365,137.209],[184.465,137.613],[184.5,138],[184.5,141],[184.471,141.293],[184.386,141.574],[184.247,141.833],[184.061,142.061],[183.833,142.247],[183.574,142.386],[183.293,142.471],[183,142.5],[182.707,142.529],[182.426,142.614],[182.167,142.753],[181.939,142.939],[181.753,143.167],[181.614,143.426],[181.529,143.707],[181.5,144],[181.5,147],[181.5,150],[181.5,153],[181.529,153.293],[181.614,153.574],[181.753,153.833],[181.939,154.061],[182.167,154.247],[182.426,154.386],[182.707,154.471],[183,154.5],[183.293,154.471],[183.574,154.386],[183.833,154.247],[184.061,154.061],[184.247,153.833],[184.386,153.574],[184.471,153.293],[184.5,153],[184.5,150],[184.5,147],[184.535,146.613],[184.635,146.209],[184.788,145.798],[184.985,145.39],[185.215,144.996],[185.467,144.626],[185.733,144.291],[186,144],[186.268,143.709],[186.533,143.374],[186.785,143.004],[187.015,142.61],[187.212,142.202],[187.365,141.791],[187.465,141.387],[187.5,141],[187.5,138],[187.5,135],[187.529,134.707],[187.614,134.426],[187.753,134.167],[187.939,133.939],[188.167,133.753],[188.426,133.614],[188.707,133.529],[189,133.5],[189.293,133.471],[189.574,133.386],[189.833,133.247],[190.061,133.061],[190.247,132.833],[190.386,132.574],[190.471,132.293],[190.5,132],[190.5,129],[190.471,128.707],[190.386,128.426],[190.247,128.167],[190.061,127.939],[189.833,127.753],[189.574,127.614],[189.293,127.529],[189,127.5],[188.707,127.471],[188.426,127.386],[188.167,127.247],[187.939,127.061],[187.753,126.833],[187.614,126.574],[187.529,126.293],[187.5,126],[187.5,123],[187.5,120],[187.5,117],[187.5,114],[187.5,111],[187.5,108],[187.5,105],[187.5,102],[187.5,99],[187.5,96],[187.5,93],[187.5,90],[187.535,89.613],[187.635,89.209],[187.788,88.798],[187.985,88.39],[188.215,87.996],[188.467,87.626],[188.733,87.291],[189,87],[189.291,86.733],[189.626,86.467],[189.996,86.215],[190.39,85.985],[190.798,85.788],[191.209,85.635],[191.613,85.535],[192,85.5],[192.293,85.529],[192.574,85.614],[192.833,85.753],[193.061,85.939],[193.247,86.167],[193.386,86.426],[193.471,86.707],[193.5,87],[193.5,90],[193.5,93],[193.5,96],[193.5,99],[193.5,102],[193.5,105],[193.5,108],[193.5,111],[193.5,114],[193.5,117],[193.5,120],[193.5,123],[193.5,126],[193.5,129],[193.5,132],[193.535,132.387],[193.635,132.791],[193.788,133.202],[193.985,133.61],[194.215,134.004],[194.467,134.374],[194.733,134.709],[195,135],[195.268,135.291],[195.533,135.626],[195.785,135.996],[196.015,136.39],[196.212,136.798],[196.365,137.209],[196.465,137.613],[196.5,138],[196.5,141],[196.5,144],[196.465,144.387],[196.365,144.791],[196.212,145.202],[196.015,145.61],[195.785,146.004],[195.533,146.374],[195.268,146.709],[195,147],[194.709,147.268],[194.374,147.533],[194.004,147.785],[193.61,148.015],[193.202,148.212],[192.791,148.365],[192.387,148.465],[192,148.5],[191.613,148.535],[191.209,148.635],[190.798,148.788],[190.39,148.985],[189.996,149.215],[189.626,149.467],[189.291,149.733],[189,150],[188.733,150.291],[188.467,150.626],[188.215,150.996],[187.985,151.39],[187.788,151.798],[187.635,152.209],[187.535,152.613],[187.5,153],[187.465,153.387],[187.365,153.791],[187.212,154.202],[187.015,154.61],[186.785,155.004],[186.533,155.374],[186.268,155.709],[186,156],[185.709,156.268],[185.374,156.533],[185.004,156.785],[184.61,157.015],[184.202,157.212],[183.791,157.365],[183.387,157.465],[183,157.5],[180,157.5],[177,157.5],[176.707,157.471],[176.426,157.386],[176.167,157.247],[175.939,157.061],[175.753,156.833],[175.614,156.574],[175.529,156.293],[175.5,156],[175.529,155.707],[175.614,155.426],[175.753,155.167],[175.939,154.939],[176.167,154.753],[176.426,154.614],[176.707,154.529],[177,154.5],[177.293,154.471],[177.574,154.386],[177.833,154.247],[178.061,154.061],[178.247,153.833],[178.386,153.574],[178.471,153.293],[178.5,153],[178.471,152.707],[178.386,152.426],[178.247,152.167],[178.061,151.939],[177.833,151.753],[177.574,151.614],[177.293,151.529],[177,151.5],[174,151.5],[171,151.5],[168,151.5],[165,151.5],[162,151.5],[159,151.5],[156,151.5],[153,151.5],[150,151.5]],"Anchors":[[150,151.5],[149.613,151.535],[149.209,151.635],[148.798,151.788],[148.39,151.985],[147.996,152.215],[147.626,152.467],[147.291,152.733],[147,153],[144,156],[143.733,156.291],[143.467,156.626],[143.215,156.996],[142.985,157.39],[142.788,157.798],[142.635,158.209],[142.535,158.613],[142.5,159],[142.465,159.387],[142.365,159.791],[142.212,160.202],[142.015,160.61],[141.785,161.004],[141.533,161.374],[141.268,161.709],[141,162],[140.709,162.268],[140.374,162.533],[140.004,162.785],[139.61,163.015],[139.202,163.212],[138.791,163.365],[138.387,163.465],[138,163.5],[137.707,163.471],[137.426,163.386],[137.167,163.247],[136.939,163.061],[136.753,162.833],[136.614,162.574],[136.529,162.293],[136.5,162],[136.5,159],[136.535,158.613],[136.635,158.209],[136.788,157.798],[136.985,157.39],[137.215,156.996],[137.467,156.626],[137.733,156.291],[138,156],[141,153],[144,150],[147,147],[150,144],[153,141],[153.268,140.709],[153.533,140.374],[153.785,140.004],[154.015,139.61],[154.212,139.202],[154.365,138.791],[154.465,138.387],[154.5,138],[154.535,137.613],[154.635,137.209],[154.788,136.798],[154.985,136.39],[155.215,135.996],[155.467,135.626],[155.733,135.291],[156,135],[159,132],[162,129],[165,126],[165.291,125.733],[165.626,125.467],[165.996,125.215],[166.39,124.985],[166.798,124.788],[167.209,124.635],[167.613,124.536],[168,124.5],[171,124.5],[171.387,124.536],[171.791,124.635],[172.202,124.788],[172.61,124.985],[173.004,125.215],[173.374,125.467],[173.709,125.733],[174,126],[177,129],[180,132],[183,135],[183.268,135.291],[183.533,135.626],[183.785,135.996],[184.015,136.39],[184.212,136.798],[184.365,137.209],[184.465,137.613],[184.5,138],[184.5,141],[184.471,141.293],[184.386,141.574],[184.247,141.833],[184.061,142.061],[183.833,142.247],[183.574,142.386],[183.293,142.471],[183,142.5],[182.707,142.529],[182.426,142.614],[182.167,142.753],[181.939,142.939],[181.753,143.167],[181.614,143.426],[181.529,143.707],[181.5,144],[181.5,147],[181.5,150],[181.5,153],[181.529,153.293],[181.614,153.574],[181.753,153.833],[181.939,154.061],[182.167,154.247],[182.426,154.386],[182.707,154.471],[183,154.5],[183.293,154.471],[183.574,154.386],[183.833,154.247],[184.061,154.061],[184.247,153.833],[184.386,153.574],[184.471,153.293],[184.5,153],[184.5,150],[184.5,147],[184.535,146.613],[184.635,146.209],[184.788,145.798],[184.985,145.39],[185.215,144.996],[185.467,144.626],[185.733,144.291],[186,144],[186.268,143.709],[186.533,143.374],[186.785,143.004],[187.015,142.61],[187.212,142.202],[187.365,141.791],[187.465,141.387],[187.5,141],[187.5,138],[187.5,135],[187.529,134.707],[187.614,134.426],[187.753,134.167],[187.939,133.939],[188.167,133.753],[188.426,133.614],[188.707,133.529],[189,133.5],[189.293,133.471],[189.574,133.386],[189.833,133.247],[190.061,133.061],[190.247,132.833],[190.386,132.574],[190.471,132.293],[190.5,132],[190.5,129],[190.471,128.707],[190.386,128.426],[190.247,128.167],[190.061,127.939],[189.833,127.753],[189.574,127.614],[189.293,127.529],[189,127.5],[188.707,127.471],[188.426,127.386],[188.167,127.247],[187.939,127.061],[187.753,126.833],[187.614,126.574],[187.529,126.293],[187.5,126],[187.5,123],[187.5,120],[187.5,117],[187.5,114],[187.5,111],[187.5,108],[187.5,105],[187.5,102],[187.5,99],[187.5,96],[187.5,93],[187.5,90],[187.535,89.613],[187.635,89.209],[187.788,88.798],[187.985,88.39],[188.215,87.996],[188.467,87.626],[188.733,87.291],[189,87],[189.291,86.733],[189.626,86.467],[189.996,86.215],[190.39,85.985],[190.798,85.788],[191.209,85.635],[191.613,85.535],[192,85.5],[192.293,85.529],[192.574,85.614],[192.833,85.753],[193.061,85.939],[193.247,86.167],[193.386,86.426],[193.471,86.707],[193.5,87],[193.5,90],[193.5,93],[193.5,96],[193.5,99],[193.5,102],[193.5,105],[193.5,108],[193.5,111],[193.5,114],[193.5,117],[193.5,120],[193.5,123],[193.5,126],[193.5,129],[193.5,132],[193.535,132.387],[193.635,132.791],[193.788,133.202],[193.985,133.61],[194.215,134.004],[194.467,134.374],[194.733,134.709],[195,135],[195.268,135.291],[195.533,135.626],[195.785,135.996],[196.015,136.39],[196.212,136.798],[196.365,137.209],[196.465,137.613],[196.5,138],[196.5,141],[196.5,144],[196.465,144.387],[196.365,144.791],[196.212,145.202],[196.015,145.61],[195.785,146.004],[195.533,146.374],[195.268,146.709],[195,147],[194.709,147.268],[194.374,147.533],[194.004,147.785],[193.61,148.015],[193.202,148.212],[192.791,148.365],[192.387,148.465],[192,148.5],[191.613,148.535],[191.209,148.635],[190.798,148.788],[190.39,148.985],[189.996,149.215],[189.626,149.467],[189.291,149.733],[189,150],[188.733,150.291],[188.467,150.626],[188.215,150.996],[187.985,151.39],[187.788,151.798],[187.635,152.209],[187.535,152.613],[187.5,153],[187.465,153.387],[187.365,153.791],[187.212,154.202],[187.015,154.61],[186.785,155.004],[186.533,155.374],[186.268,155.709],[186,156],[185.709,156.268],[185.374,156.533],[185.004,156.785],[184.61,157.015],[184.202,157.212],[183.791,157.365],[183.387,157.465],[183,157.5],[180,157.5],[177,157.5],[176.707,157.471],[176.426,157.386],[176.167,157.247],[175.939,157.061],[175.753,156.833],[175.614,156.574],[175.529,156.293],[175.5,156],[175.529,155.707],[175.614,155.426],[175.753,155.167],[175.939,154.939],[176.167,154.753],[176.426,154.614],[176.707,154.529],[177,154.5],[177.293,154.471],[177.574,154.386],[177.833,154.247],[178.061,154.061],[178.247,153.833],[178.386,153.574],[178.471,153.293],[178.5,153],[178.471,152.707],[178.386,152.426],[178.247,152.167],[178.061,151.939],[177.833,151.753],[177.574,151.614],[177.293,151.529],[177,151.5],[174,151.5],[171,151.5],[168,151.5],[165,151.5],[162,151.5],[159,151.5],[156,151.5],[153,151.5],[150,151.5]],"Anchors":[[150,151.5],[149.613,151.535],[149.209,151.635],[148.798,151.788],[148.39,151.985],[147.996,152.215],[147.626,152.467],[147.291,152.733],[147,153],[144,156],[143.733,156.291],[143.467,156.626],[143.215,156.996],[142.985,157.39],[142.788,157.798],[142.635,158.209],[142.535,158.613],[142.5,159],[142.465,159.387],[142.365,159.791],[142.212,160.202],[142.015,160.61],[141.785,161.004],[141.533,161.374],[141.268,161.709],[141,162],[140.709,162.268],[140.374,162.533],[140.004,162.785],[139.61,163.015],[139.202,163.212],[138.791,163.365],[138.387,163.465],[138,163.5],[137.707,163.471],[137.426,163.386],[137.167,163.247],[136.939,163.061],[136.753,162.833],[136.614,162.574],[136.529,162.293],[136.5,162],[136.5,159],[136.535,158.613],[136.635,158.209],[136.788,157.798],[136.985,157.39],[137.215,156.996],[137.467,156.626],[137.733,156.291],[138,156],[141,153],[144,150],[147,147],[150,144],[153,141],[153.268,140.709],[153.533,140.374],[153.785,140.004],[154.015,139.61],[154.212,139.202],[154.365,138.791],[154.465,138.387],[154.5,138],[154.535,137.613],[154.635,137.209],[154.788,136.798],[154.985,136.39],[155.215,135.996],[155.467,135.626],[155.733,135.291],[156,135],[159,132],[162,129],[165,126],[165.291,125.733],[165.626,125.467],[165.996,125.215],[166.39,124.985],[166.798,124.788],[167.209,124.635],[167.613,124.536],[168,124.5],[171,124.5],[171.387,124.536],[171.791,124.635],[172.202,124.788],[172.61,124.985],[173.004,125.215],[173.374,125.467],[173.709,125.733],[174,126],[177,129],[180,132],[183,135],[183.268,135.291],[183.533,135.626],[183.785,135.996],[184.015,136.39],[184.212,136.798],[184.365,137.209],[184.465,137.613],[184.5,138],[184.5,141],[184.471,141.293],[184.386,141.574],[184.247,141.833],[184.061,142.061],[183.833,142.247],[183.574,142.386],[183.293,142.471],[183,142.5],[182.707,142.529],[182.426,142.614],[182.167,142.753],[181.939,142.939],[181.753,143.167],[181.614,143.426],[181.529,143.707],[181.5,144],[181.5,147],[181.5,150],[181.5,153],[181.529,153.293],[181.614,153.574],[181.753,153.833],[181.939,154.061],[182.167,154.247],[182.426,154.386],[182.707,154.471],[183,154.5],[183.293,154.471],[183.574,154.386],[183.833,154.247],[184.061,154.061],[184.247,153.833],[184.386,153.574],[184.471,153.293],[184.5,153],[184.5,150],[184.5,147],[184.535,146.613],[184.635,146.209],[184.788,145.798],[184.985,145.39],[185.215,144.996],[185.467,144.626],[185.733,144.291],[186,144],[186.268,143.709],[186.533,143.374],[186.785,143.004],[187.015,142.61],[187.212,142.202],[187.365,141.791],[187.465,141.387],[187.5,141],[187.5,138],[187.5,135],[187.529,134.707],[187.614,134.426],[187.753,134.167],[187.939,133.939],[188.167,133.753],[188.426,133.614],[188.707,133.529],[189,133.5],[189.293,133.471],[189.574,133.386],[189.833,133.247],[190.061,133.061],[190.247,132.833],[190.386,132.574],[190.471,132.293],[190.5,132],[190.5,129],[190.471,128.707],[190.386,128.426],[190.247,128.167],[190.061,127.939],[189.833,127.753],[189.574,127.614],[189.293,127.529],[189,127.5],[188.707,127.471],[188.426,127.386],[188.167,127.247],[187.939,127.061],[187.753,126.833],[187.614,126.574],[187.529,126.293],[187.5,126],[187.5,123],[187.5,120],[187.5,117],[187.5,114],[187.5,111],[187.5,108],[187.5,105],[187.5,102],[187.5,99],[187.5,96],[187.5,93],[187.5,90],[187.535,89.613],[187.635,89.209],[187.788,88.798],[187.985,88.39],[188.215,87.996],[188.467,87.626],[188.733,87.291],[189,87],[189.291,86.733],[189.626,86.467],[189.996,86.215],[190.39,85.985],[190.798,85.788],[191.209,85.635],[191.613,85.535],[192,85.5],[192.293,85.529],[192.574,85.614],[192.833,85.753],[193.061,85.939],[193.247,86.167],[193.386,86.426],[193.471,86.707],[193.5,87],[193.5,90],[193.5,93],[193.5,96],[193.5,99],[193.5,102],[193.5,105],[193.5,108],[193.5,111],[193.5,114],[193.5,117],[193.5,120],[193.5,123],[193.5,126],[193.5,129],[193.5,132],[193.535,132.387],[193.635,132.791],[193.788,133.202],[193.985,133.61],[194.215,134.004],[194.467,134.374],[194.733,134.709],[195,135],[195.268,135.291],[195.533,135.626],[195.785,135.996],[196.015,136.39],[196.212,136.798],[196.365,137.209],[196.465,137.613],[196.5,138],[196.5,141],[196.5,144],[196.465,144.387],[196.365,144.791],[196.212,145.202],[196.015,145.61],[195.785,146.004],[195.533,146.374],[195.268,146.709],[195,147],[194.709,147.268],[194.374,147.533],[194.004,147.785],[193.61,148.015],[193.202,148.212],[192.791,148.365],[192.387,148.465],[192,148.5],[191.613,148.535],[191.209,148.635],[190.798,148.788],[190.39,148.985],[189.996,149.215],[189.626,149.467],[189.291,149.733],[189,150],[188.733,150.291],[188.467,150.626],[188.215,150.996],[187.985,151.39],[187.788,151.798],[187.635,152.209],[187.535,152.613],[187.5,153],[187.465,153.387],[187.365,153.791],[187.212,154.202],[187.015,154.61],[186.785,155.004],[186.533,155.374],[186.268,155.709],[186,156],[185.709,156.268],[185.374,156.533],[185.004,156.785],[184.61,157.015],[184.202,157.212],[183.791,157.365],[183.387,157.465],[183,157.5],[180,157.5],[177,157.5],[176.707,157.471],[176.426,157.386],[176.167,157.247],[175.939,157.061],[175.753,156.833],[175.614,156.574],[175.529,156.293],[175.5,156],[175.529,155.707],[175.614,155.426],[175.753,155.167],[175.939,154.939],[176.167,154.753],[176.426,154.614],[176.707,154.529],[177,154.5],[177.293,154.471],[177.574,154.386],[177.833,154.247],[178.061,154.061],[178.247,153.833],[178.386,153.574],[178.471,153.293],[178.5,153],[178.471,152.707],[178.386,152.426],[178.247,152.167],[178.061,151.939],[177.833,151.753],[177.574,151.614],[177.293,151.529],[177,151.5],[174,151.5],[171,151.5],[168,151.5],[165,151.5],[162,151.5],[159,151.5],[156,151.5],[153,151.5],[150,151.5]],"TotalLength":312.15,"AnchorCount":352,"Anchors":[[150,151.5],[149.613,151.535],[149.209,151.635],[148.798,151.788],[148.39,151.985],[147.996,152.215],[147.626,152.467],[147.291,152.733],[147,153],[144,156],[143.733,156.291],[143.467,156.626],[143.215,156.996],[142.985,157.39],[142.788,157.798],[142.635,158.209],[142.535,158.613],[142.5,159],[142.465,159.387],[142.365,159.791],[142.212,160.202],[142.015,160.61],[141.785,161.004],[141.533,161.374],[141.268,161.709],[141,162],[140.709,162.268],[140.374,162.533],[140.004,162.785],[139.61,163.015],[139.202,163.212],[138.791,163.365],[138.387,163.465],[138,163.5],[137.707,163.471],[137.426,163.386],[137.167,163.247],[136.939,163.061],[136.753,162.833],[136.614,162.574],[136.529,162.293],[136.5,162],[136.5,159],[136.535,158.613],[136.635,158.209],[136.788,157.798],[136.985,157.39],[137.215,156.996],[137.467,156.626],[137.733,156.291],[138,156],[141,153],[144,150],[147,147],[150,144],[153,141],[153.268,140.709],[153.533,140.374],[153.785,140.004],[154.015,139.61],[154.212,139.202],[154.365,138.791],[154.465,138.387],[154.5,138],[154.535,137.613],[154.635,137.209],[154.788,136.798],[154.985,136.39],[155.215,135.996],[155.467,135.626],[155.733,135.291],[156,135],[159,132],[162,129],[165,126],[165.291,125.733],[165.626,125.467],[165.996,125.215],[166.39,124.985],[166.798,124.788],[167.209,124.635],[167.613,124.536],[168,124.5],[171,124.5],[171.387,124.536],[171.791,124.635],[172.202,124.788],[172.61,124.985],[173.004,125.215],[173.374,125.467],[173.709,125.733],[174,126],[177,129],[180,132],[183,135],[183.268,135.291],[183.533,135.626],[183.785,135.996],[184.015,136.39],[184.212,136.798],[184.365,137.209],[184.465,137.613],[184.5,138],[184.5,141],[184.471,141.293],[184.386,141.574],[184.247,141.833],[184.061,142.061],[183.833,142.247],[183.574,142.386],[183.293,142.471],[183,142.5],[182.707,142.529],[182.426,142.614],[182.167,142.753],[181.939,142.939],[181.753,143.167],[181.614,143.426],[181.529,143.707],[181.5,144],[181.5,147],[181.5,150],[181.5,153],[181.529,153.293],[181.614,153.574],[181.753,153.833],[181.939,154.061],[182.167,154.247],[182.426,154.386],[182.707,154.471],[183,154.5],[183.293,154.471],[183.574,154.386],[183.833,154.247],[184.061,154.061],[184.247,153.833],[184.386,153.574],[184.471,153.293],[184.5,153],[184.5,150],[184.5,147],[184.535,146.613],[184.635,146.209],[184.788,145.798],[184.985,145.39],[185.215,144.996],[185.467,144.626],[185.733,144.291],[186,144],[186.268,143.709],[186.533,143.374],[186.785,143.004],[187.015,142.61],[187.212,142.202],[187.365,141.791],[187.465,141.387],[187.5,141],[187.5,138],[187.5,135],[187.529,134.707],[187.614,134.426],[187.753,134.167],[187.939,133.939],[188.167,133.753],[188.426,133.614],[188.707,133.529],[189,133.5],[189.293,133.471],[189.574,133.386],[189.833,133.247],[190.061,133.061],[190.247,132.833],[190.386,132.574],[190.471,132.293],[190.5,132],[190.5,129],[190.471,128.707],[190.386,128.426],[190.247,128.167],[190.061,127.939],[189.833,127.753],[189.574,127.614],[189.293,127.529],[189,127.5],[188.707,127.471],[188.426,127.386],[188.167,127.247],[187.939,127.061],[187.753,126.833],[187.614,126.574],[187.529,126.293],[187.5,126],[187.5,123],[187.5,120],[187.5,117],[187.5,114],[187.5,111],[187.5,108],[187.5,105],[187.5,102],[187.5,99],[187.5,96],[187.5,93],[187.5,90],[187.535,89.613],[187.635,89.209],[187.788,88.798],[187.985,88.39],[188.215,87.996],[188.467,87.626],[188.733,87.291],[189,87],[189.291,86.733],[189.626,86.467],[189.996,86.215],[190.39,85.985],[190.798,85.788],[191.209,85.635],[191.613,85.535],[192,85.5],[192.293,85.529],[192.574,85.614],[192.833,85.753],[193.061,85.939],[193.247,86.167],[193.386,86.426],[193.471,86.707],[193.5,87],[193.5,90],[193.5,93],[193.5,96],[193.5,99],[193.5,102],[193.5,105],[193.5,108],[193.5,111],[193.5,114],[193.5,117],[193.5,120],[193.5,123],[193.5,126],[193.5,129],[193.5,132],[193.535,132.387],[193.635,132.791],[193.788,133.202],[193.985,133.61],[194.215,134.004],[194.467,134.374],[194.733,134.709],[195,135],[195.268,135.291],[195.533,135.626],[195.785,135.996],[196.015,136.39],[196.212,136.798],[196.365,137.209],[196.465,137.613],[196.5,138],[196.5,141],[196.5,144],[196.465,144.387],[196.365,144.791],[196.212,145.202],[196.015,145.61],[195.785,146.004],[195.533,146.374],[195.268,146.709],[195,147],[194.709,147.268],[194.374,147.533],[194.004,147.785],[193.61,148.015],[193.202,148.212],[192.791,148.365],[192.387,148.465],[192,148.5],[191.613,148.535],[191.209,148.635],[190.798,148.788],[190.39,148.985],[189.996,149.215],[189.626,149.467],[189.291,149.733],[189,150],[188.733,150.291],[188.467,150.626],[188.215,150.996],[187.985,151.39],[187.788,151.798],[187.635,152.209],[187.535,152.613],[187.5,153],[187.465,153.387],[187.365,153.791],[187.212,154.202],[187.015,154.61],[186.785,155.004],[186.533,155.374],[186.268,155.709],[186,156],[185.709,156.268],[185.374,156.533],[185.004,156.785],[184.61,157.015],[184.202,157.212],[183.791,157.365],[183.387,157.465],[183,157.5],[180,157.5],[177,157.5],[176.707,157.471],[176.426,157.386],[176.167,157.247],[175.939,157.061],[175.753,156.833],[175.614,156.574],[175.529,156.293],[175.5,156],[175.529,155.707],[175.614,155.426],[175.753,155.167],[175.939,154.939],[176.167,154.753],[176.426,154.614],[176.707,154.529],[177,154.5],[177.293,154.471],[177.574,154.386],[177.833,154.247],[178.061,154.061],[178.247,153.833],[178.386,153.574],[178.471,153.293],[178.5,153],[178.471,152.707],[178.386,152.426],[178.247,152.167],[178.061,151.939],[177.833,151.753],[177.574,151.614],[177.293,151.529],[177,151.5],[174,151.5],[171,151.5],[168,151.5],[165,151.5],[162,151.5],[159,151.5],[156,151.5],[153,151.5],[150,151.5]],"LapStartAnchorIndex":235,"MicroBoundaryAnchor":[235,262,340,8,53,89,125,190,202],"Walls":[[137.835,162,137.835,159],[135.165,162,135.165,159],[135.165,162,135.2,162.444],[135.2,162.444,135.304,162.876],[135.304,162.876,135.474,163.287],[135.474,163.287,135.706,163.666],[135.706,163.666,135.995,164.005],[135.995,164.005,136.334,164.294],[136.334,164.294,136.713,164.526],[136.713,164.526,137.124,164.696],[137.124,164.696,137.557,164.8],[137.557,164.8,138,164.835],[168,125.835,171,125.835],[168,123.165,171,123.165],[180.165,144,180.165,147],[182.835,144,182.835,147],[180.165,144,180.2,143.557],[180.2,143.557,180.304,143.124],[180.304,143.124,180.474,142.713],[180.474,142.713,180.706,142.334],[180.706,142.334,180.995,141.995],[180.995,141.995,181.334,141.706],[181.334,141.706,181.713,141.474],[181.713,141.474,182.124,141.304],[182.124,141.304,182.557,141.2],[182.557,141.2,183,141.165],[183,143.835,183.444,143.8],[183.444,143.8,183.876,143.696],[183.876,143.696,184.287,143.526],[184.287,143.526,184.666,143.294],[184.666,143.294,185.005,143.005],[185.005,143.005,185.294,142.666],[185.294,142.666,185.526,142.287],[185.526,142.287,185.696,141.876],[185.696,141.876,185.8,141.444],[185.8,141.444,185.835,141],[183.165,138,183.165,141],[185.835,138,185.835,141],[180.165,150,180.165,153],[182.835,150,182.835,153],[180.165,147,180.165,150],[182.835,147,182.835,150],[183,155.835,182.557,155.8],[182.557,155.8,182.124,155.696],[182.124,155.696,181.713,155.526],[181.713,155.526,181.334,155.294],[181.334,155.294,180.995,155.005],[180.995,155.005,180.706,154.666],[180.706,154.666,180.474,154.287],[180.474,154.287,180.304,153.876],[180.304,153.876,180.2,153.444],[180.2,153.444,180.165,153],[185.835,153,185.8,153.444],[185.8,153.444,185.696,153.876],[185.696,153.876,185.526,154.287],[185.526,154.287,185.294,154.666],[185.294,154.666,185.005,155.005],[185.005,155.005,184.666,155.294],[184.666,155.294,184.287,155.526],[184.287,155.526,183.876,155.696],[183.876,155.696,183.444,155.8],[183.444,155.8,183,155.835],[183.165,150,183.165,153],[185.835,150,185.835,153],[188.835,141,188.835,138],[186.165,141,186.165,138],[185.835,150,185.835,147],[183.165,150,183.165,147],[191.835,132,191.835,129],[189.165,132,189.165,129],[191.835,132,191.8,132.444],[191.8,132.444,191.696,132.876],[191.696,132.876,191.526,133.287],[191.526,133.287,191.294,133.666],[191.294,133.666,191.005,134.005],[191.005,134.005,190.666,134.294],[190.666,134.294,190.287,134.526],[190.287,134.526,189.876,134.696],[189.876,134.696,189.444,134.8],[189.444,134.8,189,134.835],[189,132.165,188.557,132.2],[188.557,132.2,188.124,132.304],[188.124,132.304,187.713,132.474],[187.713,132.474,187.334,132.706],[187.334,132.706,186.995,132.995],[186.995,132.995,186.706,133.334],[186.706,133.334,186.474,133.713],[186.474,133.713,186.304,134.124],[186.304,134.124,186.2,134.557],[186.2,134.557,186.165,135],[188.835,138,188.835,135],[186.165,138,186.165,135],[189,126.165,189.444,126.2],[189.444,126.2,189.876,126.304],[189.876,126.304,190.287,126.474],[190.287,126.474,190.666,126.706],[190.666,126.706,191.005,126.995],[191.005,126.995,191.294,127.334],[191.294,127.334,191.526,127.713],[191.526,127.713,191.696,128.124],[191.696,128.124,191.8,128.557],[191.8,128.557,191.835,129],[189,128.835,188.557,128.8],[188.557,128.8,188.124,128.696],[188.124,128.696,187.713,128.526],[187.713,128.526,187.334,128.294],[187.334,128.294,186.995,128.005],[186.995,128.005,186.706,127.666],[186.706,127.666,186.474,127.287],[186.474,127.287,186.304,126.876],[186.304,126.876,186.2,126.444],[186.2,126.444,186.165,126],[188.835,96,188.835,93],[186.165,96,186.165,93],[188.835,99,188.835,96],[186.165,99,186.165,96],[188.835,102,188.835,99],[186.165,102,186.165,99],[188.835,123,188.835,120],[186.165,123,186.165,120],[188.835,126,188.835,123],[186.165,126,186.165,123],[188.835,120,188.835,117],[186.165,120,186.165,117],[188.835,117,188.835,114],[186.165,117,186.165,114],[188.835,114,188.835,111],[186.165,114,186.165,111],[188.835,111,188.835,108],[186.165,111,186.165,108],[188.835,108,188.835,105],[186.165,108,186.165,105],[188.835,105,188.835,102],[186.165,105,186.165,102],[192.165,87,192.165,90],[194.835,87,194.835,90],[194.835,87,194.8,86.557],[194.8,86.557,194.696,86.124],[194.696,86.124,194.526,85.713],[194.526,85.713,194.294,85.334],[194.294,85.334,194.005,84.995],[194.005,84.995,193.666,84.706],[193.666,84.706,193.287,84.474],[193.287,84.474,192.876,84.304],[192.876,84.304,192.444,84.2],[192.444,84.2,192,84.165],[188.835,93,188.835,90],[186.165,93,186.165,90],[192.165,120,192.165,123],[194.835,120,194.835,123],[192.165,117,192.165,120],[194.835,117,194.835,120],[192.165,114,192.165,117],[194.835,114,194.835,117],[192.165,93,192.165,96],[194.835,93,194.835,96],[192.165,90,192.165,93],[194.835,90,194.835,93],[192.165,96,192.165,99],[194.835,96,194.835,99],[192.165,99,192.165,102],[194.835,99,194.835,102],[192.165,102,192.165,105],[194.835,102,194.835,105],[192.165,105,192.165,108],[194.835,105,194.835,108],[192.165,108,192.165,111],[194.835,108,194.835,111],[192.165,111,192.165,114],[194.835,111,194.835,114],[194.835,126,194.835,123],[192.165,126,192.165,123],[194.835,129,194.835,126],[192.165,129,192.165,126],[195.165,138,195.165,141],[197.835,138,197.835,141],[192.165,129,192.165,132],[194.835,129,194.835,132],[183,156.165,180,156.165],[183,158.835,180,158.835],[195.165,141,195.165,144],[197.835,141,197.835,144],[177,150.165,174,150.165],[177,152.835,174,152.835],[177,150.165,177.444,150.2],[177.444,150.2,177.876,150.304],[177.876,150.304,178.287,150.474],[178.287,150.474,178.666,150.706],[178.666,150.706,179.005,150.995],[179.005,150.995,179.294,151.334],[179.294,151.334,179.526,151.713],[179.526,151.713,179.696,152.124],[179.696,152.124,179.8,152.557],[179.8,152.557,179.835,153],[179.835,153,179.8,153.444],[179.8,153.444,179.696,153.876],[179.696,153.876,179.526,154.287],[179.526,154.287,179.294,154.666],[179.294,154.666,179.005,155.005],[179.005,155.005,178.666,155.294],[178.666,155.294,178.287,155.526],[178.287,155.526,177.876,155.696],[177.876,155.696,177.444,155.8],[177.444,155.8,177,155.835],[177,153.165,176.557,153.2],[176.557,153.2,176.124,153.304],[176.124,153.304,175.713,153.474],[175.713,153.474,175.334,153.706],[175.334,153.706,174.995,153.995],[174.995,153.995,174.706,154.334],[174.706,154.334,174.474,154.713],[174.474,154.713,174.304,155.124],[174.304,155.124,174.2,155.557],[174.2,155.557,174.165,156],[174.165,156,174.2,156.444],[174.2,156.444,174.304,156.876],[174.304,156.876,174.474,157.287],[174.474,157.287,174.706,157.666],[174.706,157.666,174.995,158.005],[174.995,158.005,175.334,158.294],[175.334,158.294,175.713,158.526],[175.713,158.526,176.124,158.696],[176.124,158.696,176.557,158.8],[176.557,158.8,177,158.835],[180,156.165,177,156.165],[180,158.835,177,158.835],[171,152.835,174,152.835],[171,150.165,174,150.165],[168,152.835,171,152.835],[168,150.165,171,150.165],[165,152.835,168,152.835],[165,150.165,168,150.165],[162,152.835,165,152.835],[162,150.165,165,150.165],[159,152.835,162,152.835],[159,150.165,162,150.165],[156,152.835,159,152.835],[156,150.165,159,150.165],[153,152.835,156,152.835],[153,150.165,156,150.165],[150,152.835,153,152.835],[150,150.165,153,150.165]],"Kerbs":[]}