{
    "Id": "authored_closure_2063058048",
    "StageId": 3,
    "StageName": "AuthoredTireFuel",
    "AuthoredCardCount": 77,
    "ClosureCardCount": 5,
    "Seed": 2063058048,
    "Placements": [
        {
            "ShapeId": "STRAIGHT_1x1",
            "X": 49,
            "Y": 48,
            "Facing": 6
        },
        {
            "ShapeId": "CURVE_1x1",
            "X": 50,
            "Y": 48,
            "Facing": 4
        },
        {
            "ShapeId": "STRAIGHT_1x1",
            "X": 50,
            "Y": 49,
            "Facing": 4
        },
        {
            "ShapeId": "STRAIGHT_DIAG_1x1",
            "X": 45,
            "Y": 47,
            "Facing": 6
        },
        {
            "ShapeId": "CURVE_DIAG_TRANS_1x1",
            "X": 46,
            "Y": 46,
            "Facing": 6
        },
        {
            "ShapeId": "CURVE_1x1",
            "X": 47,
            "Y": 46,
            "Facing": 4
        },
        {
            "ShapeId": "CURVE_1x1",
            "X": 47,
            "Y": 47,
            "Facing": 2
        },
        {
            "ShapeId": "LCURVE_1x1",
            "X": 46,
            "Y": 47,
            "Facing": 4
        },
        {
            "ShapeId": "LCURVE_1x1",
            "X": 46,
            "Y": 48,
            "Facing": 6
        },
        {
            "ShapeId": "STRAIGHT_1x1",
            "X": 47,
            "Y": 48,
            "Facing": 6
        },
        {
            "ShapeId": "STRAIGHT_1x1",
            "X": 48,
            "Y": 48,
            "Facing": 6
        },
        {
            "ShapeId": "STRAIGHT_DIAG_1x1",
            "X": 39,
            "Y": 48,
            "Facing": 6
        },
        {
            "ShapeId": "CURVE_DIAG_TRANS_1x1",
            "X": 40,
            "Y": 47,
            "Facing": 6
        },
        {
            "ShapeId": "STRAIGHT_DIAG_1x1",
            "X": 44,
            "Y": 48,
            "Facing": 2
        },
        {
            "ShapeId": "CURVE_DIAG_TRANS_1x1",
            "X": 43,
            "Y": 49,
            "Facing": 2
        },
        {
            "ShapeId": "STRAIGHT_1x1",
            "X": 41,
            "Y": 47,
            "Facing": 6
        },
        {
            "ShapeId": "CURVE_1x1",
            "X": 42,
            "Y": 47,
            "Facing": 4
        },
        {
            "ShapeId": "CURVE_1x1",
            "X": 42,
            "Y": 48,
            "Facing": 2
        },
        {
            "ShapeId": "LCURVE_1x1",
            "X": 41,
            "Y": 48,
            "Facing": 4
        },
        {
            "ShapeId": "LCURVE_1x1",
            "X": 41,
            "Y": 49,
            "Facing": 6
        },
        {
            "ShapeId": "STRAIGHT_1x1",
            "X": 42,
            "Y": 49,
            "Facing": 6
        },
        {
            "ShapeId": "STRAIGHT_1x1",
            "X": 34,
            "Y": 53,
            "Facing": 6
        },
        {
            "ShapeId": "LCURVE_1x1",
            "X": 35,
            "Y": 53,
            "Facing": 0
        },
        {
            "ShapeId": "LCURVE_DIAG_TRANS_1x1",
            "X": 35,
            "Y": 52,
            "Facing": 4
        },
        {
            "ShapeId": "STRAIGHT_DIAG_1x1",
            "X": 36,
            "Y": 51,
            "Facing": 6
        },
        {
            "ShapeId": "STRAIGHT_DIAG_1x1",
            "X": 37,
            "Y": 50,
            "Facing": 6
        },
        {
            "ShapeId": "STRAIGHT_DIAG_1x1",
            "X": 38,
            "Y": 49,
            "Facing": 6
        },
        {
            "ShapeId": "STRAIGHT_1x1",
            "X": 32,
            "Y": 54,
            "Facing": 0
        },
        {
            "ShapeId": "CURVE_1x1",
            "X": 32,
            "Y": 53,
            "Facing": 6
        },
        {
            "ShapeId": "STRAIGHT_1x1",
            "X": 33,
            "Y": 53,
            "Facing": 6
        },
        {
            "ShapeId": "STRAIGHT_1x1",
            "X": 32,
            "Y": 65,
            "Facing": 0
        },
        {
            "ShapeId": "STRAIGHT_1x1",
            "X": 32,
            "Y": 64,
            "Facing": 0
        },
        {
            "ShapeId": "STRAIGHT_1x1",
            "X": 32,
            "Y": 63,
            "Facing": 0
        },
        {
            "ShapeId": "STRAIGHT_1x1",
            "X": 32,
            "Y": 56,
            "Facing": 0
        },
        {
            "ShapeId": "STRAIGHT_1x1",
            "X": 32,
            "Y": 55,
            "Facing": 0
        },
        {
            "ShapeId": "STRAIGHT_1x1",
            "X": 32,
            "Y": 57,
            "Facing": 0
        },
        {
            "ShapeId": "STRAIGHT_1x1",
            "X": 32,
            "Y": 58,
            "Facing": 0
        },
        {
            "ShapeId": "STRAIGHT_1x1",
            "X": 32,
            "Y": 59,
            "Facing": 0
        },
        {
            "ShapeId": "STRAIGHT_1x1",
            "X": 32,
            "Y": 60,
            "Facing": 0
        },
        {
            "ShapeId": "STRAIGHT_1x1",
            "X": 32,
            "Y": 61,
            "Facing": 0
        },
        {
            "ShapeId": "STRAIGHT_1x1",
            "X": 32,
            "Y": 62,
            "Facing": 0
        },
        {
            "ShapeId": "STRAIGHT_1x1",
            "X": 32,
            "Y": 66,
            "Facing": 4
        },
        {
            "ShapeId": "STRAIGHT_1x1",
            "X": 32,
            "Y": 67,
            "Facing": 4
        },
        {
            "ShapeId": "STRAIGHT_1x1",
            "X": 32,
            "Y": 68,
            "Facing": 4
        },
        {
            "ShapeId": "STRAIGHT_1x1",
            "X": 32,
            "Y": 70,
            "Facing": 0
        },
        {
            "ShapeId": "STRAIGHT_1x1",
            "X": 32,
            "Y": 69,
            "Facing": 0
        },
        {
            "ShapeId": "STRAIGHT_1x1",
            "X": 33,
            "Y": 72,
            "Facing": 2
        },
        {
            "ShapeId": "CURVE_1x1",
            "X": 32,
            "Y": 72,
            "Facing": 0
        },
        {
            "ShapeId": "STRAIGHT_1x1",
            "X": 32,
            "Y": 71,
            "Facing": 0
        },
        {
            "ShapeId": "STRAIGHT_1x1",
            "X": 37,
            "Y": 71,
            "Facing": 2
        },
        {
            "ShapeId": "CURVE_DIAG_TRANS_1x1",
            "X": 36,
            "Y": 71,
            "Facing": 6
        },
        {
            "ShapeId": "CURVE_DIAG_TRANS_1x1",
            "X": 35,
            "Y": 72,
            "Facing": 2
        },
        {
            "ShapeId": "STRAIGHT_1x1",
            "X": 34,
            "Y": 72,
            "Facing": 2
        },
        {
            "ShapeId": "STRAIGHT_1x1",
            "X": 38,
            "Y": 71,
            "Facing": 6
        },
        {
            "ShapeId": "STRAIGHT_1x1",
            "X": 39,
            "Y": 71,
            "Facing": 6
        },
        {
            "ShapeId": "STRAIGHT_1x1",
            "X": 40,
            "Y": 71,
            "Facing": 6
        },
        {
            "ShapeId": "STRAIGHT_1x1",
            "X": 41,
            "Y": 71,
            "Facing": 6
        },
        {
            "ShapeId": "STRAIGHT_1x1",
            "X": 45,
            "Y": 72,
            "Facing": 2
        },
        {
            "ShapeId": "LCURVE_DIAG_TRANS_1x1",
            "X": 44,
            "Y": 72,
            "Facing": 6
        },
        {
            "ShapeId": "LCURVE_DIAG_TRANS_1x1",
            "X": 43,
            "Y": 71,
            "Facing": 2
        },
        {
            "ShapeId": "STRAIGHT_1x1",
            "X": 42,
            "Y": 71,
            "Facing": 2
        },
        {
            "ShapeId": "STRAIGHT_1x1",
            "X": 46,
            "Y": 72,
            "Facing": 6
        },
        {
            "ShapeId": "STRAIGHT_1x1",
            "X": 47,
            "Y": 72,
            "Facing": 6
        },
        {
            "ShapeId": "STRAIGHT_DIAG_1x1",
            "X": 54,
            "Y": 65,
            "Facing": 4
        },
        {
            "ShapeId": "CURVE_DIAG_TRANS_1x1",
            "X": 55,
            "Y": 66,
            "Facing": 4
        },
        {
            "ShapeId": "STRAIGHT_1x1",
            "X": 55,
            "Y": 67,
            "Facing": 4
        },
        {
            "ShapeId": "STRAIGHT_1x1",
            "X": 55,
            "Y": 68,
            "Facing": 4
        },
        {
            "ShapeId": "STRAIGHT_1x1",
            "X": 55,
            "Y": 69,
            "Facing": 4
        },
        {
            "ShapeId": "STRAIGHT_1x1",
            "X": 55,
            "Y": 70,
            "Facing": 4
        },
        {
            "ShapeId": "LCURVE_DIAG_TRANS_1x1",
            "X": 55,
            "Y": 71,
            "Facing": 0
        },
        {
            "ShapeId": "CURVE_DIAG_TRANS_1x1",
            "X": 54,
            "Y": 72,
            "Facing": 2
        },
        {
            "ShapeId": "STRAIGHT_1x1",
            "X": 53,
            "Y": 72,
            "Facing": 2
        },
        {
            "ShapeId": "STRAIGHT_1x1",
            "X": 52,
            "Y": 72,
            "Facing": 2
        },
        {
            "ShapeId": "STRAIGHT_1x1",
            "X": 51,
            "Y": 72,
            "Facing": 2
        },
        {
            "ShapeId": "STRAIGHT_1x1",
            "X": 50,
            "Y": 72,
            "Facing": 2
        },
        {
            "ShapeId": "STRAIGHT_1x1",
            "X": 49,
            "Y": 72,
            "Facing": 2
        },
        {
            "ShapeId": "STRAIGHT_1x1",
            "X": 48,
            "Y": 72,
            "Facing": 2
        },
        {
            "ShapeId": "STRAIGHT_1x1",
            "X": 51,
            "Y": 62,
            "Facing": 4
        },
        {
            "ShapeId": "LCURVE_1x1",
            "X": 51,
            "Y": 63,
            "Facing": 6
        },
        {
            "ShapeId": "LCURVE_DIAG_TRANS_1x1",
            "X": 52,
            "Y": 63,
            "Facing": 2
        },
        {
            "ShapeId": "STRAIGHT_DIAG_1x1",
            "X": 53,
            "Y": 64,
            "Facing": 4
        },
        {
            "ShapeId": "STRAIGHT_1x1",
            "X": 50,
            "Y": 58,
            "Facing": 4
        },
        {
            "ShapeId": "CURVE_DIAG_TRANS_1x1",
            "X": 50,
            "Y": 59,
            "Facing": 0
        },
        {
            "ShapeId": "CURVE_DIAG_TRANS_1x1",
            "X": 51,
            "Y": 60,
            "Facing": 4
        },
        {
            "ShapeId": "STRAIGHT_1x1",
            "X": 51,
            "Y": 61,
            "Facing": 4
        },
        {
            "ShapeId": "STRAIGHT_1x1",
            "X": 50,
            "Y": 57,
            "Facing": 0
        },
        {
            "ShapeId": "STRAIGHT_1x1",
            "X": 50,
            "Y": 56,
            "Facing": 0
        },
        {
            "ShapeId": "STRAIGHT_1x1",
            "X": 50,
            "Y": 55,
            "Facing": 0
        },
        {
            "ShapeId": "STRAIGHT_1x1",
            "X": 50,
            "Y": 54,
            "Facing": 0
        },
        {
            "ShapeId": "STRAIGHT_1x1",
            "X": 50,
            "Y": 53,
            "Facing": 0
        },
        {
            "ShapeId": "STRAIGHT_1x1",
            "X": 50,
            "Y": 52,
            "Facing": 0
        },
        {
            "ShapeId": "STRAIGHT_1x1",
            "X": 50,
            "Y": 51,
            "Facing": 0
        },
        {
            "ShapeId": "STRAIGHT_1x1",
            "X": 50,
            "Y": 50,
            "Facing": 0
        }
    ],
    "ClosureSegments": [
        {
        },
        {
            "Anchors": [
                {
                    "X": 151.5,
                    "Z": 171.0
                },
                {
                    "X": 151.5,
                    "Z": 174.0
                }
            ]
        },
        {
            "Anchors": [
                {
                    "X": 151.5,
                    "Z": 168.0
                },
                {
                    "X": 151.5,
                    "Z": 171.0
                }
            ]
        },
        {
            "Anchors": [
                {
                    "X": 151.5,
                    "Z": 165.0
                },
                {
                    "X": 151.5,
                    "Z": 168.0
                }
            ]
        },
        {
            "Anchors": [
                {
                    "X": 151.5,
                    "Z": 162.0
                },
                {
                    "X": 151.5,
                    "Z": 165.0
                }
            ]
        },
        {
            "Anchors": [
                {
                    "X": 151.5,
                    "Z": 159.0
                },
                {
                    "X": 151.5,
                    "Z": 162.0
                }
            ]
        },
        {
            "Anchors": [
                {
                    "X": 151.5,
                    "Z": 156.0
                },
                {
                    "X": 151.5,
                    "Z": 159.0
                }
            ]
        },
        {
            "Anchors": [
                {
                    "X": 151.5,
                    "Z": 153.0
                },
                {
                    "X": 151.5,
                    "Z": 156.0
                }
            ]
        },
        {
            "Anchors": [
                {
                    "X": 151.5,
                    "Z": 150.0
                },
                {
                    "X": 151.5,
                    "Z": 153.0
                }
            ]
        }
    ],"Anchors":[[151.5,150],[151.5,153],[151.5,156],[151.5,159],[151.5,162],[151.5,165],[151.5,168],[151.5,171],[151.5,174],[151.5,177],[151.535,177.387],[151.635,177.791],[151.788,178.202],[151.985,178.61],[152.215,179.004],[152.467,179.374],[152.733,179.709],[153,180],[153.268,180.291],[153.533,180.626],[153.785,180.996],[154.015,181.39],[154.212,181.798],[154.365,182.209],[154.465,182.613],[154.5,183],[154.5,186],[154.5,189],[154.529,189.293],[154.614,189.574],[154.753,189.833],[154.939,190.061],[155.167,190.247],[155.426,190.386],[155.707,190.471],[156,190.5],[156.387,190.535],[156.791,190.635],[157.202,190.788],[157.61,190.985],[158.004,191.215],[158.374,191.467],[158.709,191.733],[159,192],[162,195],[165,198],[165.268,198.291],[165.533,198.626],[165.785,198.996],[166.015,199.39],[166.212,199.798],[166.365,200.209],[166.465,200.613],[166.5,201],[166.5,204],[166.5,207],[166.5,210],[166.5,213],[166.465,213.387],[166.365,213.791],[166.212,214.202],[166.015,214.61],[165.785,215.004],[165.533,215.374],[165.268,215.709],[165,216],[164.709,216.268],[164.374,216.533],[164.004,216.785],[163.61,217.015],[163.202,217.212],[162.791,217.365],[162.387,217.465],[162,217.5],[159,217.5],[156,217.5],[153,217.5],[150,217.5],[147,217.5],[144,217.5],[141,217.5],[138,217.5],[135,217.5],[134.613,217.465],[134.209,217.365],[133.798,217.212],[133.39,217.015],[132.996,216.785],[132.626,216.533],[132.291,216.268],[132,216],[131.709,215.733],[131.374,215.467],[131.004,215.215],[130.61,214.985],[130.202,214.788],[129.791,214.635],[129.387,214.535],[129,214.5],[126,214.5],[123,214.5],[120,214.5],[117,214.5],[114,214.5],[111,214.5],[110.613,214.535],[110.209,214.635],[109.798,214.788],[109.39,214.985],[108.996,215.215],[108.626,215.467],[108.291,215.733],[108,216],[107.709,216.268],[107.374,216.533],[107.004,216.785],[106.61,217.015],[106.202,217.212],[105.791,217.365],[105.387,217.465],[105,217.5],[102,217.5],[99,217.5],[98.707,217.471],[98.426,217.386],[98.167,217.247],[97.939,217.061],[97.753,216.833],[97.614,216.574],[97.529,216.293],[97.5,216],[97.5,213],[97.5,210],[97.5,207],[97.5,204],[97.5,201],[97.5,198],[97.5,195],[97.5,192],[97.5,189],[97.5,186],[97.5,183],[97.5,180],[97.5,177],[97.5,174],[97.5,171],[97.5,168],[97.5,165],[97.5,162],[97.529,161.707],[97.614,161.426],[97.753,161.167],[97.939,160.939],[98.167,160.753],[98.426,160.614],[98.707,160.529],[99,160.5],[102,160.5],[105,160.5],[105.293,160.471],[105.574,160.386],[105.833,160.247],[106.061,160.061],[106.247,159.833],[106.386,159.574],[106.471,159.293],[106.5,159],[106.536,158.613],[106.635,158.209],[106.788,157.798],[106.985,157.39],[107.215,156.996],[107.467,156.626],[107.733,156.291],[108,156],[111,153],[114,150],[117,147],[120,144],[120.291,143.733],[120.626,143.467],[120.996,143.215],[121.39,142.985],[121.798,142.788],[122.209,142.635],[122.613,142.535],[123,142.5],[126,142.5],[126.293,142.529],[126.574,142.614],[126.833,142.753],[127.061,142.939],[127.247,143.167],[127.386,143.426],[127.471,143.707],[127.5,144],[127.471,144.293],[127.386,144.574],[127.247,144.833],[127.061,145.061],[126.833,145.247],[126.574,145.386],[126.293,145.471],[126,145.5],[125.707,145.529],[125.426,145.614],[125.167,145.753],[124.939,145.939],[124.753,146.167],[124.614,146.426],[124.529,146.707],[124.5,147],[124.529,147.293],[124.614,147.574],[124.753,147.833],[124.939,148.061],[125.167,148.247],[125.426,148.386],[125.707,148.471],[126,148.5],[129,148.5],[129.387,148.465],[129.791,148.365],[130.202,148.212],[130.61,148.015],[131.004,147.785],[131.374,147.533],[131.709,147.268],[132,147],[135,144],[138,141],[138.291,140.733],[138.626,140.467],[138.996,140.215],[139.39,139.985],[139.798,139.788],[140.209,139.635],[140.613,139.535],[141,139.5],[141.293,139.529],[141.574,139.614],[141.833,139.753],[142.061,139.939],[142.247,140.167],[142.386,140.426],[142.471,140.707],[142.5,141],[142.471,141.293],[142.386,141.574],[142.247,141.833],[142.061,142.061],[141.833,142.247],[141.574,142.386],[141.293,142.471],[141,142.5],[140.707,142.529],[140.426,142.614],[140.167,142.753],[139.939,142.939],[139.753,143.167],[139.614,143.426],[139.529,143.707],[139.5,144],[139.529,144.293],[139.614,144.574],[139.753,144.833],[139.939,145.061],[140.167,145.247],[140.426,145.386],[140.707,145.471],[141,145.5],[144,145.5],[147,145.5],[150,145.5],[150.293,145.529],[150.574,145.614],[150.833,145.753],[151.061,145.939],[151.247,146.167],[151.386,146.426],[151.471,146.707],[151.5,147],[151.5,150]],"TotalLength":286.443,"AnchorCount":283,"Anchors":[[151.5,150],[151.5,153],[151.5,156],[151.5,159],[151.5,162],[151.5,165],[151.5,168],[151.5,171],[151.5,174],[151.5,177],[151.535,177.387],[151.635,177.791],[151.788,178.202],[151.985,178.61],[152.215,179.004],[152.467,179.374],[152.733,179.709],[153,180],[153.268,180.291],[153.533,180.626],[153.785,180.996],[154.015,181.39],[154.212,181.798],[154.365,182.209],[154.465,182.613],[154.5,183],[154.5,186],[154.5,189],[154.529,189.293],[154.614,189.574],[154.753,189.833],[154.939,190.061],[155.167,190.247],[155.426,190.386],[155.707,190.471],[156,190.5],[156.387,190.535],[156.791,190.635],[157.202,190.788],[157.61,190.985],[158.004,191.215],[158.374,191.467],[158.709,191.733],[159,192],[162,195],[165,198],[165.268,198.291],[165.533,198.626],[165.785,198.996],[166.015,199.39],[166.212,199.798],[166.365,200.209],[166.465,200.613],[166.5,201],[166.5,204],[166.5,207],[166.5,210],[166.5,213],[166.465,213.387],[166.365,213.791],[166.212,214.202],[166.015,214.61],[165.785,215.004],[165.533,215.374],[165.268,215.709],[165,216],[164.709,216.268],[164.374,216.533],[164.004,216.785],[163.61,217.015],[163.202,217.212],[162.791,217.365],[162.387,217.465],[162,217.5],[159,217.5],[156,217.5],[153,217.5],[150,217.5],[147,217.5],[144,217.5],[141,217.5],[138,217.5],[135,217.5],[134.613,217.465],[134.209,217.365],[133.798,217.212],[133.39,217.015],[132.996,216.785],[132.626,216.533],[132.291,216.268],[132,216],[131.709,215.733],[131.374,215.467],[131.004,215.215],[130.61,214.985],[130.202,214.788],[129.791,214.635],[129.387,214.535],[129,214.5],[126,214.5],[123,214.5],[120,214.5],[117,214.5],[114,214.5],[111,214.5],[110.613,214.535],[110.209,214.635],[109.798,214.788],[109.39,214.985],[108.996,215.215],[108.626,215.467],[108.291,215.733],[108,216],[107.709,216.268],[107.374,216.533],[107.004,216.785],[106.61,217.015],[106.202,217.212],[105.791,217.365],[105.387,217.465],[105,217.5],[102,217.5],[99,217.5],[98.707,217.471],[98.426,217.386],[98.167,217.247],[97.939,217.061],[97.753,216.833],[97.614,216.574],[97.529,216.293],[97.5,216],[97.5,213],[97.5,210],[97.5,207],[97.5,204],[97.5,201],[97.5,198],[97.5,195],[97.5,192],[97.5,189],[97.5,186],[97.5,183],[97.5,180],[97.5,177],[97.5,174],[97.5,171],[97.5,168],[97.5,165],[97.5,162],[97.529,161.707],[97.614,161.426],[97.753,161.167],[97.939,160.939],[98.167,160.753],[98.426,160.614],[98.707,160.529],[99,160.5],[102,160.5],[105,160.5],[105.293,160.471],[105.574,160.386],[105.833,160.247],[106.061,160.061],[106.247,159.833],[106.386,159.574],[106.471,159.293],[106.5,159],[106.536,158.613],[106.635,158.209],[106.788,157.798],[106.985,157.39],[107.215,156.996],[107.467,156.626],[107.733,156.291],[108,156],[111,153],[114,150],[117,147],[120,144],[120.291,143.733],[120.626,143.467],[120.996,143.215],[121.39,142.985],[121.798,142.788],[122.209,142.635],[122.613,142.535],[123,142.5],[126,142.5],[126.293,142.529],[126.574,142.614],[126.833,142.753],[127.061,142.939],[127.247,143.167],[127.386,143.426],[127.471,143.707],[127.5,144],[127.471,144.293],[127.386,144.574],[127.247,144.833],[127.061,145.061],[126.833,145.247],[126.574,145.386],[126.293,145.471],[126,145.5],[125.707,145.529],[125.426,145.614],[125.167,145.753],[124.939,145.939],[124.753,146.167],[124.614,146.426],[124.529,146.707],[124.5,147],[124.529,147.293],[124.614,147.574],[124.753,147.833],[124.939,148.061],[125.167,148.247],[125.426,148.386],[125.707,148.471],[126,148.5],[129,148.5],[129.387,148.465],[129.791,148.365],[130.202,148.212],[130.61,148.015],[131.004,147.785],[131.374,147.533],[131.709,147.268],[132,147],[135,144],[138,141],[138.291,140.733],[138.626,140.467],[138.996,140.215],[139.39,139.985],[139.798,139.788],[140.209,139.635],[140.613,139.535],[141,139.5],[141.293,139.529],[141.574,139.614],[141.833,139.753],[142.061,139.939],[142.247,140.167],[142.386,140.426],[142.471,140.707],[142.5,141],[142.471,141.293],[142.386,141.574],[142.247,141.833],[142.061,142.061],[141.833,142.247],[141.574,142.386],[141.293,142.471],[141,142.5],[140.707,142.529],[140.426,142.614],[140.167,142.753],[139.939,142.939],[139.753,143.167],[139.614,143.426],[139.529,143.707],[139.5,144],[139.529,144.293],[139.614,144.574],[139.753,144.833],[139.939,145.061],[140.167,145.247],[140.426,145.386],[140.707,145.471],[141,145.5],[144,145.5],[147,145.5],[150,145.5],[150.293,145.529],[150.574,145.614],[150.833,145.753],[151.061,145.939],[151.247,146.167],[151.386,146.426],[151.471,146.707],[151.5,147],[151.5,150]],"LapStartAnchorIndex":139,"MicroBoundaryAnchor":[139,156,186,248,3,37,69,89,121],"Walls":[[150,144.165,147,144.165],[150,146.835,147,146.835],[150,144.165,150.444,144.2],[150.444,144.2,150.876,144.304],[150.876,144.304,151.287,144.474],[151.287,144.474,151.666,144.706],[151.666,144.706,152.005,144.995],[152.005,144.995,152.294,145.334],[152.294,145.334,152.526,145.713],[152.526,145.713,152.696,146.124],[152.696,146.124,152.8,146.557],[152.8,146.557,152.835,147],[152.835,150,152.835,147],[150.165,150,150.165,147],[141,138.165,141.444,138.2],[141.444,138.2,141.876,138.304],[141.876,138.304,142.287,138.474],[142.287,138.474,142.666,138.706],[142.666,138.706,143.005,138.995],[143.005,138.995,143.294,139.334],[143.294,139.334,143.526,139.713],[143.526,139.713,143.696,140.124],[143.696,140.124,143.8,140.557],[143.8,140.557,143.835,141],[143.835,141,143.8,141.444],[143.8,141.444,143.696,141.876],[143.696,141.876,143.526,142.287],[143.526,142.287,143.294,142.666],[143.294,142.666,143.005,143.005],[143.005,143.005,142.666,143.294],[142.666,143.294,142.287,143.526],[142.287,143.526,141.876,143.696],[141.876,143.696,141.444,143.8],[141.444,143.8,141,143.835],[141,141.165,140.557,141.2],[140.557,141.2,140.124,141.304],[140.124,141.304,139.713,141.474],[139.713,141.474,139.334,141.706],[139.334,141.706,138.995,141.995],[138.995,141.995,138.706,142.334],[138.706,142.334,138.474,142.713],[138.474,142.713,138.304,143.124],[138.304,143.124,138.2,143.557],[138.2,143.557,138.165,144],[138.165,144,138.2,144.444],[138.2,144.444,138.304,144.876],[138.304,144.876,138.474,145.287],[138.474,145.287,138.706,145.666],[138.706,145.666,138.995,146.005],[138.995,146.005,139.334,146.294],[139.334,146.294,139.713,146.526],[139.713,146.526,140.124,146.696],[140.124,146.696,140.557,146.8],[140.557,146.8,141,146.835],[144,144.165,141,144.165],[144,146.835,141,146.835],[147,144.165,144,144.165],[147,146.835,144,146.835],[126,141.165,123,141.165],[126,143.835,123,143.835],[126,141.165,126.444,141.2],[126.444,141.2,126.876,141.304],[126.876,141.304,127.287,141.474],[127.287,141.474,127.666,141.706],[127.666,141.706,128.005,141.995],[128.005,141.995,128.294,142.334],[128.294,142.334,128.526,142.713],[128.526,142.713,128.696,143.124],[128.696,143.124,128.8,143.557],[128.8,143.557,128.835,144],[128.835,144,128.8,144.444],[128.8,144.444,128.696,144.876],[128.696,144.876,128.526,145.287],[128.526,145.287,128.294,145.666],[128.294,145.666,128.005,146.005],[128.005,146.005,127.666,146.294],[127.666,146.294,127.287,146.526],[127.287,146.526,126.876,146.696],[126.876,146.696,126.444,146.8],[126.444,146.8,126,146.835],[126,144.165,125.557,144.2],[125.557,144.2,125.124,144.304],[125.124,144.304,124.713,144.474],[124.713,144.474,124.334,144.706],[124.334,144.706,123.995,144.995],[123.995,144.995,123.706,145.334],[123.706,145.334,123.474,145.713],[123.474,145.713,123.304,146.124],[123.304,146.124,123.2,146.557],[123.2,146.557,123.165,147],[123.165,147,123.2,147.444],[123.2,147.444,123.304,147.876],[123.304,147.876,123.474,148.287],[123.474,148.287,123.706,148.666],[123.706,148.666,123.995,149.005],[123.995,149.005,124.334,149.294],[124.334,149.294,124.713,149.526],[124.713,149.526,125.124,149.696],[125.124,149.696,125.557,149.8],[125.557,149.8,126,149.835],[129,147.165,126,147.165],[129,149.835,126,149.835],[105,159.165,102,159.165],[105,161.835,102,161.835],[105,161.835,105.444,161.8],[105.444,161.8,105.876,161.696],[105.876,161.696,106.287,161.526],[106.287,161.526,106.666,161.294],[106.666,161.294,107.005,161.005],[107.005,161.005,107.294,160.666],[107.294,160.666,107.526,160.287],[107.526,160.287,107.696,159.876],[107.696,159.876,107.8,159.444],[107.8,159.444,107.835,159],[96.165,162,96.165,165],[98.835,162,98.835,165],[96.165,162,96.2,161.557],[96.2,161.557,96.304,161.124],[96.304,161.124,96.474,160.713],[96.474,160.713,96.706,160.334],[96.706,160.334,96.995,159.995],[96.995,159.995,97.334,159.706],[97.334,159.706,97.713,159.474],[97.713,159.474,98.124,159.304],[98.124,159.304,98.557,159.2],[98.557,159.2,99,159.165],[102,159.165,99,159.165],[102,161.835,99,161.835],[96.165,195,96.165,198],[98.835,195,98.835,198],[96.165,192,96.165,195],[98.835,192,98.835,195],[96.165,189,96.165,192],[98.835,189,98.835,192],[96.165,168,96.165,171],[98.835,168,98.835,171],[96.165,165,96.165,168],[98.835,165,98.835,168],[96.165,171,96.165,174],[98.835,171,98.835,174],[96.165,174,96.165,177],[98.835,174,98.835,177],[96.165,177,96.165,180],[98.835,177,98.835,180],[96.165,180,96.165,183],[98.835,180,98.835,183],[96.165,183,96.165,186],[98.835,183,98.835,186],[96.165,186,96.165,189],[98.835,186,98.835,189],[98.835,201,98.835,198],[96.165,201,96.165,198],[98.835,204,98.835,201],[96.165,204,96.165,201],[98.835,207,98.835,204],[96.165,207,96.165,204],[96.165,210,96.165,213],[98.835,210,98.835,213],[96.165,207,96.165,210],[98.835,207,98.835,210],[99,218.835,102,218.835],[99,216.165,102,216.165],[99,218.835,98.557,218.8],[98.557,218.8,98.124,218.696],[98.124,218.696,97.713,218.526],[97.713,218.526,97.334,218.294],[97.334,218.294,96.995,218.005],[96.995,218.005,96.706,217.666],[96.706,217.666,96.474,217.287],[96.474,217.287,96.304,216.876],[96.304,216.876,96.2,216.444],[96.2,216.444,96.165,216],[96.165,213,96.165,216],[98.835,213,98.835,216],[111,215.835,114,215.835],[111,213.165,114,213.165],[102,218.835,105,218.835],[102,216.165,105,216.165],[117,213.165,114,213.165],[117,215.835,114,215.835],[120,213.165,117,213.165],[120,215.835,117,215.835],[123,213.165,120,213.165],[123,215.835,120,215.835],[126,213.165,123,213.165],[126,215.835,123,215.835],[135,218.835,138,218.835],[135,216.165,138,216.165],[126,215.835,129,215.835],[126,213.165,129,213.165],[141,216.165,138,216.165],[141,218.835,138,218.835],[144,216.165,141,216.165],[144,218.835,141,218.835],[167.835,204,167.835,201],[165.165,204,165.165,201],[167.835,207,167.835,204],[165.165,207,165.165,204],[167.835,210,167.835,207],[165.165,210,165.165,207],[167.835,213,167.835,210],[165.165,213,165.165,210],[159,218.835,162,218.835],[159,216.165,162,216.165],[156,218.835,159,218.835],[156,216.165,159,216.165],[153,218.835,156,218.835],[153,216.165,156,216.165],[150,218.835,153,218.835],[150,216.165,153,216.165],[147,218.835,150,218.835],[147,216.165,150,216.165],[144,218.835,147,218.835],[144,216.165,147,216.165],[155.835,189,155.835,186],[153.165,189,153.165,186],[153.165,189,153.2,189.444],[153.2,189.444,153.304,189.876],[153.304,189.876,153.474,190.287],[153.474,190.287,153.706,190.666],[153.706,190.666,153.995,191.005],[153.995,191.005,154.334,191.294],[154.334,191.294,154.713,191.526],[154.713,191.526,155.124,191.696],[155.124,191.696,155.557,191.8],[155.557,191.8,156,191.835],[152.835,177,152.835,174],[150.165,177,150.165,174],[155.835,186,155.835,183],[153.165,186,153.165,183],[150.165,171,150.165,174],[152.835,171,152.835,174],[150.165,168,150.165,171],[152.835,168,152.835,171],[150.165,165,150.165,168],[152.835,165,152.835,168],[150.165,162,150.165,165],[152.835,162,152.835,165],[150.165,159,150.165,162],[152.835,159,152.835,162],[150.165,156,150.165,159],[152.835,156,152.835,159],[150.165,153,150.165,156],[152.835,153,152.835,156],[150.165,150,150.165,153],[152.835,150,152.835,153]],"Kerbs":[]}